ENCHUFLA/__init__.py
ENCHUFLA/MODULES/ACADEMY/ACADEMY.HTML
ENCHUFLA/MODULES/ACADEMY/__init__.py
ENCHUFLA/MODULES/BYTES/READ.py
ENCHUFLA/MODULES/BYTES/SCAN.py
ENCHUFLA/MODULES/CLIQUE/__init__.py
ENCHUFLA/MODULES/CLIQUE/ACADEMY/__init__.py
ENCHUFLA/MODULES/CLIQUE/DUOM/__init__.py
ENCHUFLA/MODULES/CLIQUE/DUOM/ED448/BUILD_PRIVATE_KEY.py
ENCHUFLA/MODULES/CLIQUE/DUOM/ED448/BUILD_PUBLIC_KEY.py
ENCHUFLA/MODULES/CLIQUE/DUOM/ED448/SIGN.py
ENCHUFLA/MODULES/CLIQUE/DUOM/ED448/VERIFY.py
ENCHUFLA/MODULES/CLIQUE/DUOM/ED448/__init__.py
ENCHUFLA/MODULES/CLIQUE/KEG/__init__.py
ENCHUFLA/MODULES/DUOM/ED448/ED448.HTML
ENCHUFLA/MODULES/DUOM/ED448/PRIVATE_KEY/BUILD.py
ENCHUFLA/MODULES/DUOM/ED448/PRIVATE_KEY/CREATE.py
ENCHUFLA/MODULES/DUOM/ED448/PRIVATE_KEY/READ.py
ENCHUFLA/MODULES/DUOM/ED448/PRIVATE_KEY/SCAN.py
ENCHUFLA/MODULES/DUOM/ED448/PRIVATE_KEY/SEED/SPLIT.py
ENCHUFLA/MODULES/DUOM/ED448/PUBLIC_KEY/BUILD.py
ENCHUFLA/MODULES/DUOM/ED448/PUBLIC_KEY/CREATE.py
ENCHUFLA/MODULES/DUOM/ED448/PUBLIC_KEY/SCAN.py
ENCHUFLA/MODULES/DUOM/ED448/SEED_PHRASE/2048.HTML
ENCHUFLA/MODULES/DUOM/ED448/SEED_PHRASE/SEED_PHRASE.HTML
ENCHUFLA/MODULES/DUOM/ED448/SIGN/__init__.py
ENCHUFLA/MODULES/DUOM/ED448/VERIFY/__init__.py
ENCHUFLA/MODULES/KEG/__init__.py
ENCHUFLA/MODULES/KEG/STARTS/__init__.py
ENCHUFLA/MODULES/KEG/STARTS/ED448/BUILD_PRIVATE_KEY.py
ENCHUFLA/MODULES/KEG/STARTS/ED448/BUILD_PUBLIC_KEY.py
ENCHUFLA/MODULES/KEG/STARTS/ED448/SIGN.py
ENCHUFLA/MODULES/KEG/STARTS/ED448/VERIFY.py
ENCHUFLA/MODULES/KIN/__init__.py
ENCHUFLA/MODULES/QR/GENERATE.py
ENCHUFLA/MODULES/QR/_QR.HTML
ENCHUFLA/MODULES/UTF8/SCAN.py
ENCHUFLA-0.1.7.data/scripts/ENCHUFLA
ENCHUFLA-0.1.7.dist-info/LICENSE
ENCHUFLA-0.1.7.dist-info/METADATA
ENCHUFLA-0.1.7.dist-info/WHEEL
ENCHUFLA-0.1.7.dist-info/top_level.txt
ENCHUFLA-0.1.7.dist-info/RECORD
