Metadata-Version: 2.1
Name: ENCHUFLA
Version: 0.1.7
Summary: elliptic techniques
License: SSDL
License-File: LICENSE
Requires-Dist: BOTANIST
Requires-Dist: click
Requires-Dist: ecdsa
Requires-Dist: flask
Requires-Dist: pycryptodome
Requires-Dist: qrcode
